{
  "pending": [
    {
      "title": "I9: 인페르노 나인(19) - 세로형 RPG",
      "status": "single",
      "appIds": {
        "android": "com.kr.firelite"
      },
      "developer": "Leniu Technology Co., Limited",
      "icon": "https://play-lh.googleusercontent.com/mXF7HtbUud3zSsdOzFkh-zKHE5G9n2nASkBz6-d4Fqt9wMHJkP3jniIjjcOQxFwuCWJCRLeJYrxKXBs2GbuxFg",
      "searchResults": [
        {
          "title": "I9: 인페르노 나인",
          "appId": 6737500275
        },
        {
          "title": "I9: 인페르노 나인(19)",
          "appId": 6751944275
        },
        {
          "title": "베놈: 다크 벤전스",
          "appId": 1629172527
        }
      ],
      "addedAt": "2025-12-15T21:41:56.319Z"
    },
    {
      "title": "요괴잡이소대 X 대환장 MMORPG",
      "status": "single",
      "appIds": {
        "android": "com.joynexgames.btaste.google"
      },
      "developer": "JOYNEX GAMES",
      "icon": "https://play-lh.googleusercontent.com/1ofJcFK0H4D5NKStquS_vOnEvsW1VJt2Z08H2VhXVoC_LPMIhDFGsleoZFaXNjf5P2dOezXSiillV78sKzxe",
      "searchResults": [],
      "addedAt": "2025-12-15T21:42:06.897Z"
    },
    {
      "title": "전혼M",
      "status": "single",
      "appIds": {
        "android": "com.kr.jszh.google"
      },
      "developer": "HONG KONG DUCKLING TECHNOLOGY CO.,LIMITED",
      "icon": "https://play-lh.googleusercontent.com/Z8cr0vc3FVQcV7oJ8EC4-2JfynGQwJL2QVq85AiXSrlJlNBojN8_7HCWao0V5joVmg",
      "searchResults": [
        {
          "title": "비천난무",
          "appId": 6532615290
        }
      ],
      "addedAt": "2025-12-15T21:42:07.337Z"
    },
    {
      "title": "Woodturning 3D",
      "status": "single",
      "appIds": {
        "ios": "1492451796"
      },
      "developer": "Voodoo",
      "icon": "https://is1-ssl.mzstatic.com/image/thumb/Purple211/v4/b2/77/16/b2771600-f9ce-b988-f90c-c58cf330bba4/AppIcon-0-0-1x_U007emarketing-0-8-0-85-220.png/100x100bb.png",
      "searchResults": [
        {
          "title": "Wood Turning 3D - Carving Game",
          "appId": "com.Eliten.Turning"
        },
        {
          "title": "Woodturning",
          "appId": "com.BallGames.Woodturning"
        },
        {
          "title": "Wood Turning : Wood Carving 3d",
          "appId": "com.milliongames.woodturning"
        }
      ],
      "addedAt": "2025-12-15T21:42:15.806Z"
    },
    {
      "title": "Order Crazy - 음료 물 분류 순서 일치게임",
      "status": "single",
      "appIds": {
        "ios": "6751222488"
      },
      "developer": "Bitepoch",
      "icon": "https://is1-ssl.mzstatic.com/image/thumb/Purple211/v4/5f/a1/9c/5fa19c99-e40b-5f51-2cd8-e0faae45bb28/AppIcon-1.-0-0-1x_U007epad-0-1-85-220.png/100x100bb.png",
      "searchResults": [
        {
          "title": "Crazy Sort - 상품 정렬, 매치 3 퍼즐",
          "appId": "com.crazysort.supermarket.goodstriple"
        },
        {
          "title": "Crazy Juice Sort",
          "appId": "com.mobilestudio.crazyjuicesort"
        },
        {
          "title": "Get Color — Water Sort Puzzle",
          "appId": "com.zm.watersort"
        }
      ],
      "addedAt": "2025-12-15T21:42:19.242Z"
    },
    {
      "title": "Tricky Puzzle: Brain Quest",
      "status": "single",
      "appIds": {
        "ios": "6740910225"
      },
      "developer": "美玲 陆",
      "icon": "https://is1-ssl.mzstatic.com/image/thumb/Purple221/v4/19/a0/b6/19a0b6af-f9d5-6ac9-d19e-0ca3b656c349/AppIcon-0-0-1x_U007epad-0-11-0-85-220.png/100x100bb.png",
      "searchResults": [
        {
          "title": "Brain Puzzle: Tricky Quest",
          "appId": "com.fun.brain.game"
        },
        {
          "title": "Tricky Brain Puzzle: 퍼즐 두뇌 게임",
          "appId": "com.brain.puzzle.tricky.test.annoying.quest"
        },
        {
          "title": "Brain Puzzle 2: Logic Twist",
          "appId": "com.brain.logic.joygame"
        }
      ],
      "addedAt": "2025-12-15T21:42:20.179Z"
    },
    {
      "title": "돼지 키우는 중입니다 : 국내산",
      "status": "single",
      "appIds": {
        "android": "com.TrueSoft.SuperPigIdle"
      },
      "developer": "TRSOFT",
      "icon": "https://play-lh.googleusercontent.com/nwaC9smalAARJI_3UAoWPTijULoLEv3hXvrmEy2elVdnG4itE8yT3RBoobb9s5Kjl7JdiSqYBEXk196RZz0X",
      "searchResults": [],
      "addedAt": "2025-12-15T21:42:22.862Z"
    },
    {
      "title": "린M:잊혀진 유산",
      "status": "single",
      "appIds": {
        "android": "com.ujoygp.smdl"
      },
      "developer": "Ujoy Games",
      "icon": "https://play-lh.googleusercontent.com/ML2BoYMUTEO58nzKblMMzUTk8V1jUvfzXQtcIDSolx0HqdFYGUOaT9sVgxhE02WE8VrdHHbqH8RFnzhZ0MmB9w",
      "searchResults": [
        {
          "title": "린M",
          "appId": 6738077390
        }
      ],
      "addedAt": "2025-12-15T21:42:25.288Z"
    },
    {
      "title": "Archery Showdown-Aim Arena",
      "status": "single",
      "appIds": {
        "android": "com.airmin.showdown"
      },
      "developer": "Philip Fowler Labs",
      "icon": "https://play-lh.googleusercontent.com/7m29kmbYEsuBmUmi3jG6BEHMOg93BHYVQkLTD9N2kUSnUxFjx8sf5x6ShvXRXzKLlW8",
      "searchResults": [],
      "addedAt": "2025-12-15T21:42:26.184Z"
    },
    {
      "title": "몬스터 스토리：전설의 시작",
      "status": "single",
      "appIds": {
        "android": "com.kostr.bkm"
      },
      "developer": "광저우 화성 디지털 테크놀로지 유한회사",
      "icon": "https://play-lh.googleusercontent.com/RO7_m0bMvs9Z-o-xiTpFGpdEHgxkne3PRTHdyPfvP6aRsW7Mp4LMarVU9IHEmcmbZB0xMqPPq7a99_svMArv",
      "searchResults": [],
      "addedAt": "2025-12-15T21:42:26.516Z"
    },
    {
      "title": "헌티드 머지: 괴담",
      "status": "single",
      "appIds": {
        "android": "com.whalejoy.horrorstory.gp"
      },
      "developer": "WhaleJoy Game Limited",
      "icon": "https://play-lh.googleusercontent.com/wkdnu8OxzFFCnSZw4QO2DczjcybhyW8GOMDWh4p2NG-qXX10MD3CIZHgL2vK3mWjqg",
      "searchResults": [],
      "addedAt": "2025-12-15T21:42:27.912Z"
    },
    {
      "title": "Brainy Escape Quest",
      "status": "single",
      "appIds": {
        "android": "com.metagame.annoying.trick.brainypuzzle"
      },
      "developer": "Metagame.Ltd",
      "icon": "https://play-lh.googleusercontent.com/qaegI1S3HXIZED9psoyiFY-7F85fBHGMxNZqd4Y6wTXImBSTSWcnRKwvHRVOWQRCXwk",
      "searchResults": [],
      "addedAt": "2025-12-15T21:42:34.067Z"
    },
    {
      "title": "Color Match",
      "status": "single",
      "appIds": {
        "android": "com.JacobVanHaag.ColorMatch"
      },
      "developer": "Supersonic Studios LTD",
      "icon": "https://play-lh.googleusercontent.com/JYmlH46F5tL2S7lZ8JvlAxAz68Ei0489T13WJGb7ZFFZ3Rtif1r3I0k9G7d1E1NQQg",
      "searchResults": [
        {
          "title": "Coloring Match",
          "appId": 1586980403
        },
        {
          "title": "Water Sort Puzzle",
          "appId": 1514542157
        },
        {
          "title": "I Love Hue",
          "appId": 1081075274
        }
      ],
      "addedAt": "2025-12-15T21:42:34.451Z"
    },
    {
      "title": "Logic Car Challenge",
      "status": "single",
      "appIds": {
        "android": "com.hollywood.displayed.releases"
      },
      "developer": "DextersLab",
      "icon": "https://play-lh.googleusercontent.com/ST-IE5hl-xE1MpePigrEwe8QAsd-vUhvmbxrAnLLZyEZxRnYC2XgGXmiuPa-lcg9-oMA",
      "searchResults": [
        {
          "title": "Car Screw Escape",
          "appId": 6741799475
        },
        {
          "title": "Traffic Time Rescue: Car Jam",
          "appId": 6743150038
        },
        {
          "title": "Traffic Escape!",
          "appId": 6453522960
        }
      ],
      "addedAt": "2025-12-15T21:42:36.786Z"
    },
    {
      "title": "아쿠아 로맨스: 정렬 여행",
      "status": "single",
      "appIds": {
        "android": "com.romance.jour8ney"
      },
      "developer": "Jeet talks",
      "icon": "https://play-lh.googleusercontent.com/hg9sWaAxZ6kOWcI7NaLrnXmihZ39hMpQ7_NVaUni9qQHn5ne8dHWxocFddlANC-4_Y0Y",
      "searchResults": [],
      "addedAt": "2025-12-15T21:42:37.569Z"
    },
    {
      "title": "드로우 아레나 (Draw Arena)",
      "status": "single",
      "appIds": {
        "android": "com.kadka.battle.draw"
      },
      "developer": "SayGames Ltd",
      "icon": "https://play-lh.googleusercontent.com/8T3kunZsZzVBsRxHQGW8Ls8LZJFbgrNsv28Hd-5Z2nFSAM51tQsAO5YdtZwAIMRB1_o",
      "searchResults": [],
      "addedAt": "2025-12-15T21:42:38.402Z"
    },
    {
      "title": "Kingdom Match: Royal Adventure",
      "status": "single",
      "appIds": {
        "android": "com.gamee.kingdom.royale.match3.blast.escape"
      },
      "developer": "GameeStudio",
      "icon": "https://play-lh.googleusercontent.com/_rC8deserIKuXMyraF54oN8DUXgJPq77yKwCJv9fV5EceRT7bDugNIhufiYKZOMjYqRWOcMknkj-tGtZmsCzRok",
      "searchResults": [
        {
          "title": "시계제조공: 보석 사가 과 다이아몬드 매치 게임",
          "appId": 929195587
        },
        {
          "title": "Royal Pin: King Adventure",
          "appId": 6739935904
        },
        {
          "title": "릴리의 정원 (Lily’s Garden)",
          "appId": 1437783446
        }
      ],
      "addedAt": "2025-12-15T21:42:39.412Z"
    },
    {
      "title": "Supreme Duelist Stickman",
      "status": "single",
      "appIds": {
        "android": "com.Neurononfire.SupremeDuelist"
      },
      "developer": "Neron's Brother",
      "icon": "https://play-lh.googleusercontent.com/iRq0R9mN7eGyVENIPDk5muu76VxawBAIkFAYFqauJTFNIvUxzD1_M33HNX4GE8Qk0WqY",
      "searchResults": [
        {
          "title": "Supreme Duelist",
          "appId": 1477336151
        },
        {
          "title": "Supreme Duelist 2021",
          "appId": 6470292369
        },
        {
          "title": "Supreme Duelist 2019",
          "appId": 6447521025
        }
      ],
      "addedAt": "2025-12-15T21:42:40.170Z"
    },
    {
      "title": "소녀총사 키우기",
      "status": "single",
      "appIds": {
        "ios": "6456484806"
      },
      "developer": "Act Seven Entertainment Inc.",
      "icon": "https://is1-ssl.mzstatic.com/image/thumb/Purple221/v4/57/7e/b3/577eb375-7d4e-7564-3550-0f0a265144bf/AppIcon-1x_U007emarketing-0-8-0-85-220-0.png/100x100bb.png",
      "searchResults": [
        {
          "title": "소녀총사 키우기 : 도트 방치형 RPG",
          "appId": "com.act7ent.musket"
        },
        {
          "title": "건앤걸스 : 거너 키우기",
          "appId": "com.mouseduck.gungame"
        },
        {
          "title": "정복소녀 키우기 : 수집형 방치 RPG",
          "appId": "com.greenspring.conquestgirls"
        }
      ],
      "addedAt": "2025-12-15T22:04:19.841Z"
    },
    {
      "title": "매직 레벨 9: 탭 피아노 게임, 비트에 맞춰 춤추기",
      "status": "single",
      "appIds": {
        "ios": "1446874445"
      },
      "developer": "Kim Nguyen",
      "icon": "https://is1-ssl.mzstatic.com/image/thumb/Purple221/v4/cf/fc/0f/cffc0f4a-2a24-9554-ebdd-8a62041476ef/AppIcon-0-0-1x_U007emarketing-0-8-0-85-220.png/100x100bb.png",
      "searchResults": [
        {
          "title": "음악 피아노 7:  음악게임 & 피아노게임",
          "appId": "com.bunbunstudio.magicblocktiles"
        },
        {
          "title": "매직 타일 3: 피아노 게임 케이팝 노래",
          "appId": "com.youmusic.magictiles"
        },
        {
          "title": "피아노게임 5: 음악게임 & 음악 피아노",
          "appId": "classic.pop.piano.magic.juegos"
        }
      ],
      "addedAt": "2025-12-16T00:48:31.052Z"
    },
    {
      "title": "알고보니 무서운나날",
      "status": "single",
      "appIds": {
        "android": "pics.karaage.nichijyo"
      },
      "developer": "KARAAGE GAMES LLC.",
      "icon": "https://play-lh.googleusercontent.com/hzGcFXNxuUyT0efmXnVAd8yX5UUGByZ8lFx2mByJgoKXH-bkNYx96KaLQCWBYPxsbgQ",
      "searchResults": [
        {
          "title": "Horrorfield—멀티플레이어 생존 공포 탈출 게임",
          "appId": 1351585483
        }
      ],
      "addedAt": "2025-12-16T00:48:43.009Z"
    },
    {
      "title": "미친 타워가 되었다",
      "status": "single",
      "appIds": {
        "ios": "6746247056"
      },
      "developer": "V2R",
      "icon": "https://is1-ssl.mzstatic.com/image/thumb/Purple211/v4/9d/46/b7/9d46b708-5df7-5338-2a0e-189d17d32673/AppIcon-1x_U007emarketing-0-8-0-85-220-0.png/100x100bb.png",
      "searchResults": [
        {
          "title": "미친 타워가 되었다:노빠구 RPG",
          "appId": "com.v2r.tower.google"
        },
        {
          "title": "다크타워:전략 배틀 RPG",
          "appId": "com.rawhand.darktower"
        },
        {
          "title": "크레이지 디펜스 히어로즈: 타워디펜스 전략게임",
          "appId": "com.animocabrands.google.CrazyDefenseHeroes"
        }
      ],
      "addedAt": "2025-12-17T00:44:39.178Z"
    },
    {
      "title": "Lexico: Word Puzzle Quest",
      "status": "single",
      "appIds": {
        "ios": "6755897413"
      },
      "developer": "GO OUT-APP S.R.L",
      "icon": "https://is1-ssl.mzstatic.com/image/thumb/Purple211/v4/a6/1f/84/a61f84de-8940-15db-0584-8f4a5d83afcb/AppIcon-0-0-1x_U007emarketing-0-8-0-85-220.png/100x100bb.png",
      "searchResults": [
        {
          "title": "Crossword Quest",
          "appId": "com.gsr.wordcross"
        },
        {
          "title": "Crossword Master - Word Puzzle",
          "appId": "com.easybrain.crossword.puzzles"
        },
        {
          "title": "Crossword Quest: Word Puzzle",
          "appId": "com.voxnic.wordlink.quest"
        }
      ],
      "addedAt": "2025-12-17T00:44:42.616Z"
    },
    {
      "title": "Buildit",
      "status": "single",
      "appIds": {
        "android": "com.newbeat.gardecor"
      },
      "developer": "MINIMAX PTE. LTD.",
      "icon": "https://play-lh.googleusercontent.com/qYLdXEcN2NTk8DOIm1p5UnofHa_ZSmT7Sgw9kRNQfbgJ5PTTrg0OOhMVL2yltwRCD4s",
      "searchResults": [
        {
          "title": "Buildit - Chill Brick Game",
          "appId": 6714470154
        },
        {
          "title": "SimCity BuildIt",
          "appId": 913292932
        },
        {
          "title": "Minecraft: 나만의 세계를 꿈꾸고 만들어보세요",
          "appId": 479516143
        }
      ],
      "addedAt": "2025-12-17T00:45:01.295Z"
    },
    {
      "title": "컴투스프로야구 for 매니저",
      "status": "single",
      "appIds": {
        "ios": "682942443"
      },
      "developer": "Com2uS Corp.",
      "icon": "https://is1-ssl.mzstatic.com/image/thumb/Purple211/v4/2a/aa/9b/2aaa9b6f-2376-9114-31c9-3eb72c4200f2/AppIcon-0-0-1x_U007epad-0-1-85-220.png/100x100bb.png",
      "searchResults": [
        {
          "title": "컴투스프로야구매니저",
          "appId": "com.com2us.kbomanager.normal2.freefull.google.global.android.common"
        },
        {
          "title": "컴투스프로야구2025",
          "appId": "com.com2us.probaseball3d.normal.freefull.google.global.android.common"
        },
        {
          "title": "컴투스프로야구V25",
          "appId": "com.com2us.futurecpb.android.google.global.normal"
        }
      ],
      "addedAt": "2025-12-18T00:44:32.789Z"
    },
    {
      "title": "포켓 정렬 (Pocket Sort): 동전 병합 퍼즐",
      "status": "single",
      "appIds": {
        "android": "com.pocket.sort.coin.puzzle.game"
      },
      "developer": "SayGames Ltd",
      "icon": "https://play-lh.googleusercontent.com/blnQgZLrDseT5XsOOtloqVfgMqHLDgCMOTaqei6q9brw_D182qXvj6ahfp9Sj0FF8dlP36T7xtg42ODz5IAWlQ",
      "searchResults": [],
      "addedAt": "2025-12-18T00:45:12.009Z"
    },
    {
      "title": "Pop Piano: 리듬 게임",
      "status": "single",
      "appIds": {
        "android": "com.magic.cyber.piano.tiles.edm.musicgames"
      },
      "developer": "Cobby Labs",
      "icon": "https://play-lh.googleusercontent.com/11xNmRHrdqkAEJCotsiisr47VaK4Q4CMeJHkungv4S18mijkBXFDOiESYel8hvLl9Q",
      "searchResults": [
        {
          "title": "바운스볼 -  피아노 타일 음악 리듬게임",
          "appId": 1344702806
        },
        {
          "title": "피아노 - 음악 게임 & 클래식 연주",
          "appId": 1126477246
        },
        {
          "title": "KPop Piano Beat: Music Game",
          "appId": 6751177175
        }
      ],
      "addedAt": "2025-12-18T00:45:14.663Z"
    },
    {
      "title": "Block Puzzle - 블럭 퍼즐",
      "status": "single",
      "appIds": {
        "android": "blockpuzzle.new1010.jewelgames.puzzlegames"
      },
      "developer": "Block Puzzle Jewel Games",
      "icon": "https://play-lh.googleusercontent.com/7KOeuxJZ4nW7hchEolHcCHOWmA89-cuWzl3nr4IX74YfKtm8mMYCCNa3hl-5-2_OSxw",
      "searchResults": [
        {
          "title": "Hex Blocks Puzzle: Brain Game",
          "appId": 6756582940
        },
        {
          "title": "Blockin' Color - 블록퍼즐 와 블럭게임",
          "appId": 1621292271
        },
        {
          "title": "블록 퍼즐-재미있는 두뇌 게임",
          "appId": 1519469207
        }
      ],
      "addedAt": "2025-12-18T00:45:15.276Z"
    },
    {
      "title": "Tile Home-매치 퍼즐",
      "status": "single",
      "appIds": {
        "android": "com.tile.home.match.puzzle.game"
      },
      "developer": "Mindful Daily Puzzles",
      "icon": "https://play-lh.googleusercontent.com/gNYvOPQPkwGCMYBC2X_CVhaLDL2EOBSx8u60gKJRbvqtVoeApk1KGhKKi76cqWK9posbD3Ai1DZzj1Bdj0DIKA",
      "searchResults": [
        {
          "title": "Tile Family®:Match Puzzle Game",
          "appId": 6444056676
        },
        {
          "title": "가든 사천성 : 작은 집 꾸미기",
          "appId": 1661259827
        },
        {
          "title": "Tile Explorer - 트리플 매치",
          "appId": 6498883328
        }
      ],
      "addedAt": "2025-12-18T00:45:15.998Z"
    },
    {
      "title": "블록 컬러 매니아",
      "status": "single",
      "appIds": {
        "android": "block.color.game.jam.blocks.sort.puzzle.games.slide.free"
      },
      "developer": "Brainteaser Puzzle Game Studio",
      "icon": "https://play-lh.googleusercontent.com/fJ_pK4YX0tLme8wE7uBkRIiLtwKQTFaSQaqgNezutmVwOMrbv06lvPiHoGsAP6ApOw",
      "searchResults": [
        {
          "title": "블록 블라스트 (Block Blast)",
          "appId": 1617391485
        },
        {
          "title": "Zoo Block - 스도쿠 블록 퍼즐 게임",
          "appId": 1494148558
        },
        {
          "title": "Block Mania: Color Jam",
          "appId": 6742700461
        }
      ],
      "addedAt": "2025-12-18T00:45:16.582Z"
    },
    {
      "title": "심연의 기사",
      "status": "single",
      "appIds": {
        "android": "com.kuangbao2.rpg.kr.an"
      },
      "developer": "EACHFUNGAME",
      "icon": "https://play-lh.googleusercontent.com/X2c9C084VWDBfClFgvdmTvWnStGkZt5-HyCXP_Z5qJrYQ9-gGoeMpiNSJZ2reGHKrx6DV3rzZxueI11HXaUX",
      "searchResults": [
        {
          "title": "심연의 기사 키우기",
          "appId": 6740773558
        }
      ],
      "addedAt": "2025-12-18T00:45:17.000Z"
    },
    {
      "title": "숨은그림찾기 게임: Seek It",
      "status": "single",
      "appIds": {
        "android": "hidden.object.find.seek.search.mystery.puzzle.games.free"
      },
      "developer": "NimbleMind Network Inc.",
      "icon": "https://play-lh.googleusercontent.com/wjlDWPj_fLATFob1nDPcGy_6EEEOZwpM1tjHQnVdvzJTuHJe5y0UH173Siz1oWjGuA",
      "searchResults": [
        {
          "title": "Found It! 숨은 그림 찾기 게임",
          "appId": 1643547847
        },
        {
          "title": "추적자의 노트 숨은 그림 찾기 Seekers Notes",
          "appId": 940292587
        },
        {
          "title": "숨은그림찾기 게임 - Find It Out",
          "appId": 1643481036
        }
      ],
      "addedAt": "2025-12-18T00:45:17.464Z"
    },
    {
      "title": "POOLS™",
      "status": "single",
      "appIds": {
        "ios": "6670792878"
      },
      "developer": "Tensori",
      "icon": "https://is1-ssl.mzstatic.com/image/thumb/Purple211/v4/94/69/d7/9469d797-f088-123f-733c-98b694811961/AppIcon-0-0-1x_U007emarketing-0-8-0-85-220.png/100x100bb.png",
      "searchResults": [
        {
          "title": "The Wetrooms: Liminal Pools",
          "appId": "com.ammonite.wetrooms"
        },
        {
          "title": "8 Ball Shoot It All - 8 Pool",
          "appId": "com.square_enix.pool"
        },
        {
          "title": "Pool Strike 8 ball pool",
          "appId": "com.funiza.poolstrike"
        }
      ],
      "addedAt": "2025-12-19T00:47:47.688Z"
    },
    {
      "title": "Jade Mahjong",
      "status": "single",
      "appIds": {
        "android": "com.wonderful.mahjong"
      },
      "developer": "Wonderful  Studio",
      "icon": "https://play-lh.googleusercontent.com/AeUlLrz1-tTbkOMT_dlthT9BjZyvwMzg_bdziYgvbxpBIzL47VRKpYepkUaI8itqS_CEYXh1huWpXZvLLvdMGA",
      "searchResults": [
        {
          "title": "옥 마작 (Jade Mahjong)",
          "appId": 6752887466
        },
        {
          "title": "비타 마작(Vita Mahjong)",
          "appId": 6468921495
        },
        {
          "title": "마작 클럽 - 솔리테어 게임",
          "appId": 1565374299
        }
      ],
      "addedAt": "2025-12-19T00:48:05.367Z"
    },
    {
      "title": "Screwdom 3D",
      "status": "single",
      "appIds": {
        "android": "com.ig.screwdom"
      },
      "developer": "iKame Games - Zego Studio",
      "icon": "https://play-lh.googleusercontent.com/lrGM85RjRRh4pax0P6JbDVzXF7XeJA9PSMTpRujqqDhVgiOSInZ1l3sg0uBURw9INs8",
      "searchResults": [
        {
          "title": "Screwdom : 나사와 볼트 퍼즐",
          "appId": 6740043080
        },
        {
          "title": "Screw Sort 3D - 나사매치 게임&볼트 퍼즐",
          "appId": 6633425539
        },
        {
          "title": "나사 매치 - 볼트업 퍼즐게임",
          "appId": 6499293031
        }
      ],
      "addedAt": "2025-12-19T00:48:05.690Z"
    }
  ],
  "approved": [],
  "rejected": []
}